pubgy/__init__.py
pubgy/client.py
pubgy/constants.py
pubgy/exceptions.py
pubgy/http.py
pubgy/parse.py
pubgy/struct.py
pubgy/telemetry.py
PUBGy-1.1.6.dist-info/LICENSE
PUBGy-1.1.6.dist-info/METADATA
PUBGy-1.1.6.dist-info/WHEEL
PUBGy-1.1.6.dist-info/top_level.txt
PUBGy-1.1.6.dist-info/RECORD
