Metadata-Version: 2.1
Name: PUBGy
Version: 1.1.6
Summary: PUBG API wrapper for Python
Home-page: https://github.com/Discord-ian/pubgy
Author: Discordian
License: UNKNOWN
Platform: UNKNOWN
Classifier: Development Status :: 3 - Alpha
Classifier: License :: OSI Approved :: GNU General Public License (GPL)
Classifier: Natural Language :: English
Classifier: Programming Language :: Python :: 3.5
Classifier: Programming Language :: Python :: 3.6
Classifier: Programming Language :: Python :: 3.7
Classifier: Programming Language :: Python :: 3.8
Classifier: Operating System :: OS Independent
Classifier: Topic :: Software Development :: Libraries :: Python Modules
Requires-Python: >=3.5
Requires-Dist: asyncio
Requires-Dist: aiohttp
